slcode/Load.py
slcode/SOLVER.py
slcode/__init__.py
slcode/grid.py
slcode/love.py
slcode/spharm.py
slcode-1.0.1.dist-info/LICENCE.md
slcode-1.0.1.dist-info/METADATA
slcode-1.0.1.dist-info/WHEEL
slcode-1.0.1.dist-info/top_level.txt
slcode-1.0.1.dist-info/RECORD
