Metadata-Version: 2.1
Name: slcode
Version: 1.0.1
Summary: SL_C0de is a python library based on the matlab code SL_code. This module is used to calculate GIA over the world but alse the sediment isostasy. It include function to calculate radial symetric auto gravitational earth visco-elastic response. This module also include the possibility to resolve the Sea level equation based on the publication of Mitrovica and Austermann ... ajouter des refs. The aim of this library is to be easy to include new sources of load and link to other python lib
Home-page: https://github.com/AHenryLarroze/Py_SL_C0de
Author: Adrien Henry-Larroze
Author-email: adrien_henry@orange.fr
License: GPL-3.0
Project-URL: Homepage, https://py-sl-c0de.readthedocs.io/en/latest/
Project-URL: Source Code, https://github.com/AHenryLarroze/Py_SL_C0de
Classifier: Programming Language :: Python :: 3
Classifier: Operating System :: OS Independent
Requires-Python: >=3.8
License-File: LICENCE.md
Requires-Dist: joblib
Requires-Dist: matplotlib
Requires-Dist: numpy
Requires-Dist: plotly
Requires-Dist: pyshtools
Requires-Dist: scipy
Requires-Dist: stripy
Requires-Dist: netcdf4
